psr/lakehouse/__init__.py
psr/lakehouse/client.py
psr/lakehouse/connector.py
psr/lakehouse/exceptions.py
psr/lakehouse/metadata.py
psr/lakehouse/py.typed
psr_lakehouse-0.2.4.dist-info/METADATA
psr_lakehouse-0.2.4.dist-info/WHEEL
psr_lakehouse-0.2.4.dist-info/entry_points.txt
psr_lakehouse-0.2.4.dist-info/licenses/LICENSE
psr_lakehouse-0.2.4.dist-info/RECORD
