Metadata-Version: 2.4
Name: psr-lakehouse
Version: 0.2.4
License-File: LICENSE
Requires-Python: >=3.12
Requires-Dist: boto3>=1.39.3
Requires-Dist: pandas>=2.3.0
Requires-Dist: plotly>=5.17.0
Requires-Dist: requests-aws4auth>=1.3.1
Requires-Dist: requests>=2.32.0
Requires-Dist: streamlit>=1.48.1
